ag_draftking_utils/__init__.py
ag_draftking_utils/athena_helper.py
ag_draftking_utils/aws_utils.py
ag_draftking_utils/db_helper.py
ag_draftking_utils/formulas.py
ag_draftking_utils/get_selenium_driver.py
ag_draftking_utils/google_sheets_utils.py
ag_draftking_utils/login_to_awesemo.py
ag_draftking_utils/login_to_draftkings.py
ag_draftking_utils/login_to_fc.py
ag_draftking_utils/model_api.py
ag_draftking_utils/model_utils.py
ag_draftking_utils/odds_conversions.py
ag_draftking_utils/transforms.py
ag_draftking_utils/util.py
ag_draftking_utils-1.2.89.dist-info/METADATA
ag_draftking_utils-1.2.89.dist-info/WHEEL
ag_draftking_utils-1.2.89.dist-info/top_level.txt
ag_draftking_utils-1.2.89.dist-info/RECORD
