Metadata-Version: 2.4
Name: ag_draftking_utils
Version: 1.2.89
Summary: AG Draftking Utilities
Home-page: https://github.com/akashgoyal119/DraftKingUtils
Author: no thanks
Author-email: giantsrule93@yahoo.com>
Keywords: python,sql
Classifier: Development Status :: 1 - Planning
Classifier: Intended Audience :: Developers
Classifier: Programming Language :: Python :: 3
Classifier: Operating System :: Unix
Classifier: Operating System :: MacOS :: MacOS X
Classifier: Operating System :: Microsoft :: Windows
Requires-Dist: sqlalchemy
Requires-Dist: pymysql
Requires-Dist: selenium==3.141.0
Dynamic: author
Dynamic: author-email
Dynamic: classifier
Dynamic: home-page
Dynamic: keywords
Dynamic: requires-dist
Dynamic: summary
